client/DataIngestionClient.py
client/__init__.py
client/orchestrator_factory.py
config/__init__.py
config/data_loader_config.py
config_driven_data_ingestion-1.0.2.dist-info/licenses/LICENSE
converters/__init__.py
converters/data_type_converter.py
core/__init__.py
core/base_types.py
core/exceptions.py
core/logging_config.py
data_loaders/__init__.py
data_loaders/base_loader.py
data_loaders/csv_loader.py
data_loaders/json_loader.py
models/__init__.py
models/data_record.py
orchestrators/__init__.py
orchestrators/data_orchestrator.py
processors/__init__.py
processors/data_processor.py
utils/__init__.py
writers/__init__.py
writers/database_writer.py
config_driven_data_ingestion-1.0.2.dist-info/METADATA
config_driven_data_ingestion-1.0.2.dist-info/WHEEL
config_driven_data_ingestion-1.0.2.dist-info/entry_points.txt
config_driven_data_ingestion-1.0.2.dist-info/top_level.txt
config_driven_data_ingestion-1.0.2.dist-info/RECORD
