Metadata-Version: 2.4
Name: config-driven-data-ingestion
Version: 1.0.2
Summary: A comprehensive, config-driven data ingestion library for Python
Author-email: Sathwick <sathwick@outlook.in>
License: MIT
Project-URL: Homepage, https://github.com/sathwickreddyy/python_projects/tree/main/config_driven_loading
Project-URL: Bug Tracker, https://github.com/sathwickreddyy/python_projects/issues
Keywords: data-ingestion,ETL,csv,json,yaml,sqlalchemy,database,batch-processing
Classifier: Development Status :: 5 - Production/Stable
Classifier: Intended Audience :: Developers
Classifier: License :: OSI Approved :: MIT License
Classifier: Programming Language :: Python :: 3.10
Classifier: Programming Language :: Python :: 3.11
Classifier: Operating System :: OS Independent
Classifier: Topic :: Database
Classifier: Topic :: Software Development :: Libraries :: Python Modules
Requires-Python: >=3.10
License-File: LICENSE
Requires-Dist: sqlalchemy>=2.0.0
Requires-Dist: pydantic>=2.0.0
Requires-Dist: fastapi>=0.110.0
Requires-Dist: uvicorn>=0.22.0
Requires-Dist: python-dateutil>=2.8.2
Requires-Dist: structlog>=24.1.0
Requires-Dist: jsonpath-ng>=1.6.0
Provides-Extra: dev
Requires-Dist: pytest>=7.0.0; extra == "dev"
Requires-Dist: pytest-asyncio>=0.21.0; extra == "dev"
Requires-Dist: black>=23.0.0; extra == "dev"
Requires-Dist: flake8>=6.0.0; extra == "dev"
Requires-Dist: mypy>=1.0.0; extra == "dev"
Requires-Dist: pre-commit>=3.0.0; extra == "dev"
Provides-Extra: postgresql
Requires-Dist: psycopg2-binary>=2.9.9; extra == "postgresql"
Provides-Extra: mysql
Requires-Dist: pymysql>=1.0.0; extra == "mysql"
Provides-Extra: sqlite
Requires-Dist: aiosqlite>=0.19.0; extra == "sqlite"
Provides-Extra: oracle
Requires-Dist: cx-Oracle>=8.3.0; extra == "oracle"
Provides-Extra: all
Requires-Dist: psycopg2-binary>=2.9.9; extra == "all"
Requires-Dist: pymysql>=1.0.0; extra == "all"
Requires-Dist: aiosqlite>=0.19.0; extra == "all"
Requires-Dist: cx-Oracle>=8.3.0; extra == "all"
Dynamic: license-file
